<?xml version="1.0" encoding="utf-8" ?>
<dwsync>
<file name="bookmark.gif" server="cuckoo82.cafe24.com/shop/" local="130559325119520496" remote="130559682600000000" Dst="0" />
<file name="btn_search.gif" server="cuckoo82.cafe24.com/shop/" local="130559325118490437" remote="130559682600000000" Dst="0" />
<file name="gnb_2dbg.gif" server="cuckoo82.cafe24.com/shop/" local="130553041710000000" remote="130559682600000000" Dst="0" />
<file name="hd_nb_cart.gif" server="cuckoo82.cafe24.com/shop/" local="130553041710000000" remote="130559682600000000" Dst="0" />
<file name="hd_nb_cart2.gif" server="cuckoo82.cafe24.com/shop/" local="130559325114780225" remote="130559683200000000" Dst="0" />
<file name="hd_nb_deli.gif" server="cuckoo82.cafe24.com/shop/" local="130553041710000000" remote="130559683200000000" Dst="0" />
<file name="hd_nb_deli2.gif" server="cuckoo82.cafe24.com/shop/" local="130559325112440091" remote="130559683200000000" Dst="0" />
<file name="hd_nb_help.gif" server="cuckoo82.cafe24.com/shop/" local="130553041710000000" remote="130559683200000000" Dst="0" />
<file name="hd_nb_wish.gif" server="cuckoo82.cafe24.com/shop/" local="130553041710000000" remote="130559683200000000" Dst="0" />
<file name="hd_nb_wish2.gif" server="cuckoo82.cafe24.com/shop/" local="130559325108589871" remote="130559683200000000" Dst="0" />
<file name="icon_arw_toleft.gif" server="cuckoo82.cafe24.com/shop/" local="130553041710000000" remote="130559683200000000" Dst="0" />
<file name="icon_best.gif" server="cuckoo82.cafe24.com/shop/" local="130553041710000000" remote="130559683200000000" Dst="0" />
<file name="icon_cp.gif" server="cuckoo82.cafe24.com/shop/" local="130553041710000000" remote="130559683200000000" Dst="0" />
<file name="icon_discount.gif" server="cuckoo82.cafe24.com/shop/" local="130553041710000000" remote="130559683200000000" Dst="0" />
<file name="icon_hit.gif" server="cuckoo82.cafe24.com/shop/" local="130553041710000000" remote="130559683200000000" Dst="0" />
<file name="icon_new.gif" server="cuckoo82.cafe24.com/shop/" local="130553041710000000" remote="130559683200000000" Dst="0" />
<file name="icon_rec.gif" server="cuckoo82.cafe24.com/shop/" local="130553041710000000" remote="130559683200000000" Dst="0" />
<file name="icon_soldout.gif" server="cuckoo82.cafe24.com/shop/" local="130553041710000000" remote="130559683200000000" Dst="0" />
<file name="loading.gif" server="cuckoo82.cafe24.com/shop/" local="130553041710000000" remote="130559683200000000" Dst="0" />
<file name="no_image.gif" server="cuckoo82.cafe24.com/shop/" local="130553041710000000" remote="130559683200000000" Dst="0" />
<file name="s_star1.png" server="cuckoo82.cafe24.com/shop/" local="130553041710000000" remote="130559683200000000" Dst="0" />
<file name="s_star3.png" server="cuckoo82.cafe24.com/shop/" local="130553041710000000" remote="130559683200000000" Dst="0" />
<file name="s_star4.png" server="cuckoo82.cafe24.com/shop/" local="130553041710000000" remote="130559683200000000" Dst="0" />
<file name="s_star2.png" server="cuckoo82.cafe24.com/shop/" local="130553041710000000" remote="130559683200000000" Dst="0" />
<file name="s_star5.png" server="cuckoo82.cafe24.com/shop/" local="130553041710000000" remote="130559683200000000" Dst="0" />
<file name="ts01.gif" server="cuckoo82.cafe24.com/shop/" local="130553041710000000" remote="130559683200000000" Dst="0" />
<file name="ts02.gif" server="cuckoo82.cafe24.com/shop/" local="130553041710000000" remote="130559683200000000" Dst="0" />
<file name="ts03.gif" server="cuckoo82.cafe24.com/shop/" local="130553041710000000" remote="130559683200000000" Dst="0" />
</dwsync>